odp/dto/__init__.py
odp/dto/catalog/__init__.py
odp/dto/catalog/_rg.py
odp/dto/catalog/data_collection.py
odp/dto/catalog/dataset.py
odp/dto/catalog/observable.py
odp/dto/common/__init__.py
odp/dto/common/contact_info.py
odp/dto/common/license.py
odp/dto/metadata.py
odp/dto/registry/__init__.py
odp/dto/registry/_rg.py
odp/dto/registry/observable_class.py
odp/dto/resource.py
odp/dto/resource_registry.py
odp/dto/resource_status.py
odp/dto/validators.py
odp_dto-0.7.11.dist-info/METADATA
odp_dto-0.7.11.dist-info/WHEEL
odp_dto-0.7.11.dist-info/RECORD
