Metadata-Version: 2.1
Name: odp-dto
Version: 0.7.11
Summary: ODP Data Transfer Object
License: MIT
Author: Thomas Li Fredriksen
Author-email: thomas.fredriksen@oceandata.earth
Requires-Python: >=3.9,<4.0
Classifier: License :: OSI Approved :: MIT License
Classifier: Programming Language :: Python :: 3
Classifier: Programming Language :: Python :: 3.9
Classifier: Programming Language :: Python :: 3.10
Classifier: Programming Language :: Python :: 3.11
Classifier: Programming Language :: Python :: 3.12
Classifier: Programming Language :: Python :: 3.13
Requires-Dist: pydantic (>=2.4.2,<3.0.0)
